spacelink/__init__.py
spacelink/core/__init__.py
spacelink/core/antenna.py
spacelink/core/noise.py
spacelink/core/path.py
spacelink/core/pattern_io.py
spacelink/core/ranging.py
spacelink/core/units.py
spacelink/phy/data/modes/ccsds_tm_modes.yaml
spacelink/phy/data/perf/CCSDS_TM_RS255223_I1_CONV7-12.ber.yaml
spacelink/phy/data/perf/CCSDS_TM_RS255223_I1_CONV7-12.wer.yaml
spacelink/phy/data/perf/CCSDS_TM_RS255223_I2_CONV7-12.ber.yaml
spacelink/phy/data/perf/CCSDS_TM_RS255223_I2_CONV7-12.wer.yaml
spacelink/phy/data/perf/CCSDS_TM_RS255223_I3_CONV7-12.ber.yaml
spacelink/phy/data/perf/CCSDS_TM_RS255223_I3_CONV7-12.wer.yaml
spacelink/phy/data/perf/CCSDS_TM_RS255223_I4_CONV7-12.ber.yaml
spacelink/phy/data/perf/CCSDS_TM_RS255223_I4_CONV7-12.wer.yaml
spacelink/phy/data/perf/CCSDS_TM_RS255223_I5_CONV7-12.ber.yaml
spacelink/phy/data/perf/CCSDS_TM_RS255223_I5_CONV7-12.wer.yaml
spacelink/phy/data/perf/CCSDS_TM_TURBO1784-12_BPSK.ber.yaml
spacelink/phy/data/perf/CCSDS_TM_TURBO1784-12_BPSK.fer.yaml
spacelink/phy/data/perf/CCSDS_TM_TURBO1784-13_BPSK.ber.yaml
spacelink/phy/data/perf/CCSDS_TM_TURBO1784-13_BPSK.fer.yaml
spacelink/phy/data/perf/CCSDS_TM_TURBO1784-14_BPSK.ber.yaml
spacelink/phy/data/perf/CCSDS_TM_TURBO1784-14_BPSK.fer.yaml
spacelink/phy/data/perf/CCSDS_TM_TURBO1784-16_BPSK.ber.yaml
spacelink/phy/data/perf/CCSDS_TM_TURBO1784-16_BPSK.fer.yaml
spacelink/phy/data/perf/UNCODED_BPSK.ber.yaml
spacelink/phy/mode.py
spacelink/phy/performance.py
spacelink/phy/registry.py
spacelink-0.1.9.dist-info/METADATA
spacelink-0.1.9.dist-info/WHEEL
spacelink-0.1.9.dist-info/licenses/LICENSE
spacelink-0.1.9.dist-info/RECORD
