Metadata-Version: 2.4
Name: spacelink
Version: 0.1.9
Summary: Space link budget calculation package
License-Expression: MIT
License-File: LICENSE
Author: Jacob Portukalian
Author-email: jacob@cascade.space
Requires-Python: >=3.11
Classifier: Programming Language :: Python :: 3
Classifier: Operating System :: OS Independent
Requires-Dist: astropy (>=7.0.1,<8.0.0)
Requires-Dist: numpy (>=2.0.0,<3.0.0)
Requires-Dist: pandas (>=2.3.1,<3.0.0)
Requires-Dist: pydantic (>=2.11.7,<3.0.0)
Requires-Dist: scipy (>=1.10.0,<2.0.0)
Project-URL: Documentation, https://cascade-space-co.github.io/spacelink
Project-URL: Homepage, https://github.com/cascade-space-co/spacelink
Project-URL: issues, https://github.com/cascade-space-co/spacelink/issues
